dl_on_flink_framework/context.py
dl_on_flink_framework/node_pb2.py
dl_on_flink_framework/cluster_config.py
dl_on_flink_framework/node_service_pb2.py
dl_on_flink_framework/java_file.py
dl_on_flink_framework/sysconfig.py
dl_on_flink_framework/java_file_c.cpython-38-x86_64-linux-gnu.so
dl_on_flink_framework/node_service_pb2_grpc.py
dl_on_flink_framework/startup.py
dl_on_flink_framework/version.py
dl_on_flink_framework/__init__.py
dl_on_flink_framework/include/spscqueue.h
dl_on_flink_framework/include/java_file.h
dl_on_flink_framework/include/rw_test.h
dl_on_flink_framework-0.5.0.dist-info/top_level.txt
dl_on_flink_framework-0.5.0.dist-info/WHEEL
dl_on_flink_framework-0.5.0.dist-info/METADATA
dl_on_flink_framework-0.5.0.dist-info/RECORD
