Metadata-Version: 2.1
Name: dl-on-flink-framework
Version: 0.5.0
Home-page: https://github.com/flink-extended/dl-on-flink
License: https://www.apache.org/licenses/LICENSE-2.0
Requires-Python: >=3.6,<3.9
Requires-Dist: grpcio (>=1.24.3)
Requires-Dist: protobuf (<3.18)
